{
  "type": "File",
  "start": 0,
  "end": 591,
  "loc": {
    "start": {
      "line": 1,
      "column": 0
    },
    "end": {
      "line": 13,
      "column": 0
    }
  },
  "program": {
    "type": "Program",
    "start": 0,
    "end": 591,
    "loc": {
      "start": {
        "line": 1,
        "column": 0
      },
      "end": {
        "line": 13,
        "column": 0
      }
    },
    "sourceType": "module",
    "body": [
      {
        "type": "ImportDeclaration",
        "start": 15,
        "end": 61,
        "loc": {
          "start": {
            "line": 3,
            "column": 0
          },
          "end": {
            "line": 3,
            "column": 46
          }
        },
        "specifiers": [
          {
            "type": "ImportDefaultSpecifier",
            "start": 22,
            "end": 34,
            "loc": {
              "start": {
                "line": 3,
                "column": 7
              },
              "end": {
                "line": 3,
                "column": 19
              }
            },
            "local": {
              "type": "Identifier",
              "start": 22,
              "end": 34,
              "loc": {
                "start": {
                  "line": 3,
                  "column": 7
                },
                "end": {
                  "line": 3,
                  "column": 19
                },
                "identifierName": "TyphonEvents"
              },
              "name": "TyphonEvents"
            }
          }
        ],
        "importKind": "value",
        "source": {
          "type": "StringLiteral",
          "start": 41,
          "end": 60,
          "loc": {
            "start": {
              "line": 3,
              "column": 26
            },
            "end": {
              "line": 3,
              "column": 45
            }
          },
          "extra": {
            "rawValue": "./TyphonEvents.js",
            "raw": "'./TyphonEvents.js'"
          },
          "value": "./TyphonEvents.js"
        },
        "trailingComments": [
          {
            "type": "CommentBlock",
            "value": "*\n * Exports an instance of `TyphonEvents` which adds asynchronous capabilities to `Backbone.Events` which is used as a\n * main eventbus. Note that an instance of `TyphonEvents` is exported and is also associated to a mapped path,\n * `mainEventbus` in the SystemJS extra configuration data loaded by all TyphonJS repos in\n * `./config/config-app-paths.js`. By using a mapped path any other module may import the main eventbus via:\n * `import eventbus from 'mainEventbus';`\n ",
            "start": 63,
            "end": 541,
            "loc": {
              "start": {
                "line": 5,
                "column": 0
              },
              "end": {
                "line": 11,
                "column": 3
              }
            }
          }
        ]
      },
      {
        "type": "ExportDefaultDeclaration",
        "start": 542,
        "end": 590,
        "loc": {
          "start": {
            "line": 12,
            "column": 0
          },
          "end": {
            "line": 12,
            "column": 48
          }
        },
        "declaration": {
          "type": "NewExpression",
          "start": 557,
          "end": 589,
          "loc": {
            "start": {
              "line": 12,
              "column": 15
            },
            "end": {
              "line": 12,
              "column": 47
            }
          },
          "callee": {
            "type": "Identifier",
            "start": 561,
            "end": 573,
            "loc": {
              "start": {
                "line": 12,
                "column": 19
              },
              "end": {
                "line": 12,
                "column": 31
              },
              "identifierName": "TyphonEvents"
            },
            "name": "TyphonEvents"
          },
          "arguments": [
            {
              "type": "StringLiteral",
              "start": 574,
              "end": 588,
              "loc": {
                "start": {
                  "line": 12,
                  "column": 32
                },
                "end": {
                  "line": 12,
                  "column": 46
                }
              },
              "extra": {
                "rawValue": "mainEventbus",
                "raw": "\"mainEventbus\""
              },
              "value": "mainEventbus"
            }
          ],
          "leadingComments": [
            {
              "type": "CommentBlock",
              "value": "*\n * Exports an instance of `TyphonEvents` which adds asynchronous capabilities to `Backbone.Events` which is used as a\n * main eventbus. Note that an instance of `TyphonEvents` is exported and is also associated to a mapped path,\n * `mainEventbus` in the SystemJS extra configuration data loaded by all TyphonJS repos in\n * `./config/config-app-paths.js`. By using a mapped path any other module may import the main eventbus via:\n * `import eventbus from 'mainEventbus';`\n ",
              "start": 63,
              "end": 541,
              "loc": {
                "start": {
                  "line": 5,
                  "column": 0
                },
                "end": {
                  "line": 11,
                  "column": 3
                }
              }
            }
          ],
          "trailingComments": []
        },
        "leadingComments": [
          {
            "type": "CommentBlock",
            "value": "*\n * Exports an instance of `TyphonEvents` which adds asynchronous capabilities to `Backbone.Events` which is used as a\n * main eventbus. Note that an instance of `TyphonEvents` is exported and is also associated to a mapped path,\n * `mainEventbus` in the SystemJS extra configuration data loaded by all TyphonJS repos in\n * `./config/config-app-paths.js`. By using a mapped path any other module may import the main eventbus via:\n * `import eventbus from 'mainEventbus';`\n ",
            "start": 63,
            "end": 541,
            "loc": {
              "start": {
                "line": 5,
                "column": 0
              },
              "end": {
                "line": 11,
                "column": 3
              }
            }
          }
        ]
      }
    ],
    "directives": [
      {
        "type": "Directive",
        "start": 0,
        "end": 13,
        "loc": {
          "start": {
            "line": 1,
            "column": 0
          },
          "end": {
            "line": 1,
            "column": 13
          }
        },
        "value": {
          "type": "DirectiveLiteral",
          "start": 0,
          "end": 12,
          "loc": {
            "start": {
              "line": 1,
              "column": 0
            },
            "end": {
              "line": 1,
              "column": 12
            }
          },
          "value": "use strict",
          "extra": {
            "raw": "'use strict'",
            "rawValue": "use strict"
          }
        }
      }
    ]
  },
  "comments": [
    {
      "type": "CommentBlock",
      "value": "*\n * Exports an instance of `TyphonEvents` which adds asynchronous capabilities to `Backbone.Events` which is used as a\n * main eventbus. Note that an instance of `TyphonEvents` is exported and is also associated to a mapped path,\n * `mainEventbus` in the SystemJS extra configuration data loaded by all TyphonJS repos in\n * `./config/config-app-paths.js`. By using a mapped path any other module may import the main eventbus via:\n * `import eventbus from 'mainEventbus';`\n ",
      "start": 63,
      "end": 541,
      "loc": {
        "start": {
          "line": 5,
          "column": 0
        },
        "end": {
          "line": 11,
          "column": 3
        }
      }
    }
  ],
  "tokens": [
    {
      "type": {
        "label": "string",
        "beforeExpr": false,
        "startsExpr": true,
        "rightAssociative": false,
        "isLoop": false,
        "isAssign": false,
        "prefix": false,
        "postfix": false,
        "binop": null,
        "updateContext": null
      },
      "value": "use strict",
      "start": 0,
      "end": 12,
      "loc": {
        "start": {
          "line": 1,
          "column": 0
        },
        "end": {
          "line": 1,
          "column": 12
        }
      }
    },
    {
      "type": {
        "label": ";",
        "beforeExpr": true,
        "startsExpr": false,
        "rightAssociative": false,
        "isLoop": false,
        "isAssign": false,
        "prefix": false,
        "postfix": false,
        "binop": null,
        "updateContext": null
      },
      "start": 12,
      "end": 13,
      "loc": {
        "start": {
          "line": 1,
          "column": 12
        },
        "end": {
          "line": 1,
          "column": 13
        }
      }
    },
    {
      "type": {
        "label": "import",
        "keyword": "import",
        "beforeExpr": false,
        "startsExpr": false,
        "rightAssociative": false,
        "isLoop": false,
        "isAssign": false,
        "prefix": false,
        "postfix": false,
        "binop": null,
        "updateContext": null
      },
      "value": "import",
      "start": 15,
      "end": 21,
      "loc": {
        "start": {
          "line": 3,
          "column": 0
        },
        "end": {
          "line": 3,
          "column": 6
        }
      }
    },
    {
      "type": {
        "label": "name",
        "beforeExpr": false,
        "startsExpr": true,
        "rightAssociative": false,
        "isLoop": false,
        "isAssign": false,
        "prefix": false,
        "postfix": false,
        "binop": null
      },
      "value": "TyphonEvents",
      "start": 22,
      "end": 34,
      "loc": {
        "start": {
          "line": 3,
          "column": 7
        },
        "end": {
          "line": 3,
          "column": 19
        }
      }
    },
    {
      "type": {
        "label": "name",
        "beforeExpr": false,
        "startsExpr": true,
        "rightAssociative": false,
        "isLoop": false,
        "isAssign": false,
        "prefix": false,
        "postfix": false,
        "binop": null
      },
      "value": "from",
      "start": 36,
      "end": 40,
      "loc": {
        "start": {
          "line": 3,
          "column": 21
        },
        "end": {
          "line": 3,
          "column": 25
        }
      }
    },
    {
      "type": {
        "label": "string",
        "beforeExpr": false,
        "startsExpr": true,
        "rightAssociative": false,
        "isLoop": false,
        "isAssign": false,
        "prefix": false,
        "postfix": false,
        "binop": null,
        "updateContext": null
      },
      "value": "./TyphonEvents.js",
      "start": 41,
      "end": 60,
      "loc": {
        "start": {
          "line": 3,
          "column": 26
        },
        "end": {
          "line": 3,
          "column": 45
        }
      }
    },
    {
      "type": {
        "label": ";",
        "beforeExpr": true,
        "startsExpr": false,
        "rightAssociative": false,
        "isLoop": false,
        "isAssign": false,
        "prefix": false,
        "postfix": false,
        "binop": null,
        "updateContext": null
      },
      "start": 60,
      "end": 61,
      "loc": {
        "start": {
          "line": 3,
          "column": 45
        },
        "end": {
          "line": 3,
          "column": 46
        }
      }
    },
    {
      "type": "CommentBlock",
      "value": "*\n * Exports an instance of `TyphonEvents` which adds asynchronous capabilities to `Backbone.Events` which is used as a\n * main eventbus. Note that an instance of `TyphonEvents` is exported and is also associated to a mapped path,\n * `mainEventbus` in the SystemJS extra configuration data loaded by all TyphonJS repos in\n * `./config/config-app-paths.js`. By using a mapped path any other module may import the main eventbus via:\n * `import eventbus from 'mainEventbus';`\n ",
      "start": 63,
      "end": 541,
      "loc": {
        "start": {
          "line": 5,
          "column": 0
        },
        "end": {
          "line": 11,
          "column": 3
        }
      }
    },
    {
      "type": {
        "label": "export",
        "keyword": "export",
        "beforeExpr": false,
        "startsExpr": false,
        "rightAssociative": false,
        "isLoop": false,
        "isAssign": false,
        "prefix": false,
        "postfix": false,
        "binop": null,
        "updateContext": null
      },
      "value": "export",
      "start": 542,
      "end": 548,
      "loc": {
        "start": {
          "line": 12,
          "column": 0
        },
        "end": {
          "line": 12,
          "column": 6
        }
      }
    },
    {
      "type": {
        "label": "default",
        "keyword": "default",
        "beforeExpr": true,
        "startsExpr": false,
        "rightAssociative": false,
        "isLoop": false,
        "isAssign": false,
        "prefix": false,
        "postfix": false,
        "binop": null,
        "updateContext": null
      },
      "value": "default",
      "start": 549,
      "end": 556,
      "loc": {
        "start": {
          "line": 12,
          "column": 7
        },
        "end": {
          "line": 12,
          "column": 14
        }
      }
    },
    {
      "type": {
        "label": "new",
        "keyword": "new",
        "beforeExpr": true,
        "startsExpr": true,
        "rightAssociative": false,
        "isLoop": false,
        "isAssign": false,
        "prefix": false,
        "postfix": false,
        "binop": null,
        "updateContext": null
      },
      "value": "new",
      "start": 557,
      "end": 560,
      "loc": {
        "start": {
          "line": 12,
          "column": 15
        },
        "end": {
          "line": 12,
          "column": 18
        }
      }
    },
    {
      "type": {
        "label": "name",
        "beforeExpr": false,
        "startsExpr": true,
        "rightAssociative": false,
        "isLoop": false,
        "isAssign": false,
        "prefix": false,
        "postfix": false,
        "binop": null
      },
      "value": "TyphonEvents",
      "start": 561,
      "end": 573,
      "loc": {
        "start": {
          "line": 12,
          "column": 19
        },
        "end": {
          "line": 12,
          "column": 31
        }
      }
    },
    {
      "type": {
        "label": "(",
        "beforeExpr": true,
        "startsExpr": true,
        "rightAssociative": false,
        "isLoop": false,
        "isAssign": false,
        "prefix": false,
        "postfix": false,
        "binop": null
      },
      "start": 573,
      "end": 574,
      "loc": {
        "start": {
          "line": 12,
          "column": 31
        },
        "end": {
          "line": 12,
          "column": 32
        }
      }
    },
    {
      "type": {
        "label": "string",
        "beforeExpr": false,
        "startsExpr": true,
        "rightAssociative": false,
        "isLoop": false,
        "isAssign": false,
        "prefix": false,
        "postfix": false,
        "binop": null,
        "updateContext": null
      },
      "value": "mainEventbus",
      "start": 574,
      "end": 588,
      "loc": {
        "start": {
          "line": 12,
          "column": 32
        },
        "end": {
          "line": 12,
          "column": 46
        }
      }
    },
    {
      "type": {
        "label": ")",
        "beforeExpr": false,
        "startsExpr": false,
        "rightAssociative": false,
        "isLoop": false,
        "isAssign": false,
        "prefix": false,
        "postfix": false,
        "binop": null
      },
      "start": 588,
      "end": 589,
      "loc": {
        "start": {
          "line": 12,
          "column": 46
        },
        "end": {
          "line": 12,
          "column": 47
        }
      }
    },
    {
      "type": {
        "label": ";",
        "beforeExpr": true,
        "startsExpr": false,
        "rightAssociative": false,
        "isLoop": false,
        "isAssign": false,
        "prefix": false,
        "postfix": false,
        "binop": null,
        "updateContext": null
      },
      "start": 589,
      "end": 590,
      "loc": {
        "start": {
          "line": 12,
          "column": 47
        },
        "end": {
          "line": 12,
          "column": 48
        }
      }
    },
    {
      "type": {
        "label": "eof",
        "beforeExpr": false,
        "startsExpr": false,
        "rightAssociative": false,
        "isLoop": false,
        "isAssign": false,
        "prefix": false,
        "postfix": false,
        "binop": null,
        "updateContext": null
      },
      "start": 591,
      "end": 591,
      "loc": {
        "start": {
          "line": 13,
          "column": 0
        },
        "end": {
          "line": 13,
          "column": 0
        }
      }
    }
  ]
}